auto_reloader.py
auto_reloader-0.1.3.dist-info/LICENSE
auto_reloader-0.1.3.dist-info/WHEEL
auto_reloader-0.1.3.dist-info/METADATA
auto_reloader-0.1.3.dist-info/RECORD
