Metadata-Version: 2.1
Name: auto-reloader
Version: 0.1.3
Summary: Automatic reloading library for Jupyter
Home-page: https://github.com/moisutsu/auto-reloader
Author: moisutsu
Author-email: moisutsu@gmail.com
Requires-Python: >=3.6,<4.0
Classifier: Programming Language :: Python :: 3
Classifier: Programming Language :: Python :: 3.6
Classifier: Programming Language :: Python :: 3.7
Classifier: Programming Language :: Python :: 3.8
Classifier: Programming Language :: Python :: 3.9
Project-URL: Repository, https://github.com/moisutsu/auto-reloader
